{"v":"5.12.2","fr":60,"ip":0,"op":75,"w":48,"h":48,"nm":"Team","ddd":0,"assets":[],"layers":[{"ddd":0,"ind":1,"ty":4,"nm":"team-outline-top_s1g1_s2g1_s3g1_s4g1_background Outlines","sr":1,"ks":{"o":{"a":0,"k":100,"ix":11},"r":{"a":0,"k":0,"ix":10},"p":{"a":1,"k":[{"i":{"x":0.667,"y":1},"o":{"x":0.333,"y":0},"t":0,"s":[24,24,0],"to":[0,-0.271,0],"ti":[0,0,0]},{"i":{"x":0.667,"y":1},"o":{"x":0.333,"y":0},"t":18.068,"s":[24,22.375,0],"to":[0,0,0],"ti":[0,-0.271,0]},{"t":42.162109375,"s":[24,24,0]}],"ix":2,"l":2},"a":{"a":0,"k":[12.975,15.5,0],"ix":1,"l":2},"s":{"a":0,"k":[100,100,100],"ix":6,"l":2}},"ao":0,"shapes":[{"ty":"gr","it":[{"ind":0,"ty":"sh","ix":1,"ks":{"a":0,"k":{"i":[[0,2.453],[-2.453,0],[0,-2.453],[2.453,0]],"o":[[0,-2.453],[2.453,0],[0,2.453],[-2.453,0]],"v":[[-4.441,0],[0.001,-4.442],[4.441,0],[0.001,4.442]],"c":true},"ix":2},"nm":"Path 1","mn":"ADBE Vector Shape - Group","hd":false},{"ty":"st","c":{"a":0,"k":[0.9137254901960784,0.9294117647058824,0.9607843137254902],"ix":3},"o":{"a":0,"k":100,"ix":4},"w":{"a":0,"k":2,"ix":5},"lc":2,"lj":2,"bm":0,"nm":"Stroke 1","mn":"ADBE Vector Graphic - Stroke","hd":false},{"ty":"fl","c":{"a":0,"k":[1,1,1],"ix":4},"o":{"a":0,"k":0,"ix":5},"r":1,"bm":0,"nm":"Fill 1","mn":"ADBE Vector Graphic - Fill","hd":false},{"ty":"tr","p":{"a":0,"k":[12.975,9.442],"ix":2},"a":{"a":0,"k":[0,0],"ix":1},"s":{"a":0,"k":[100,100],"ix":3},"r":{"a":0,"k":0,"ix":6},"o":{"a":0,"k":100,"ix":7},"sk":{"a":0,"k":0,"ix":4},"sa":{"a":0,"k":0,"ix":5},"nm":"Transform"}],"nm":"Group 1","np":3,"cix":2,"bm":0,"ix":1,"mn":"ADBE Vector Group","hd":false},{"ty":"gr","it":[{"ind":0,"ty":"sh","ix":1,"ks":{"a":0,"k":{"i":[[0,-3.55],[0,0],[1.391,0],[0,0],[0,1.356],[-3.642,0],[0,0]],"o":[[0,0],[0,1.356],[0,0],[-1.391,0],[0,-3.55],[0,0],[3.642,0]],"v":[[7.975,1.986],[7.975,1.986],[5.456,4.442],[-5.456,4.442],[-7.975,1.986],[-1.38,-4.442],[1.38,-4.442]],"c":true},"ix":2},"nm":"Path 1","mn":"ADBE Vector Shape - Group","hd":false},{"ty":"st","c":{"a":0,"k":[0.9137254901960784,0.9294117647058824,0.9607843137254902],"ix":3},"o":{"a":0,"k":100,"ix":4},"w":{"a":0,"k":2,"ix":5},"lc":2,"lj":2,"bm":0,"nm":"Stroke 1","mn":"ADBE Vector Graphic - Stroke","hd":false},{"ty":"fl","c":{"a":0,"k":[1,1,1],"ix":4},"o":{"a":0,"k":0,"ix":5},"r":1,"bm":0,"nm":"Fill 1","mn":"ADBE Vector Graphic - Fill","hd":false},{"ty":"tr","p":{"a":0,"k":[12.975,21.559],"ix":2},"a":{"a":0,"k":[0,0],"ix":1},"s":{"a":0,"k":[100,100],"ix":3},"r":{"a":0,"k":0,"ix":6},"o":{"a":0,"k":100,"ix":7},"sk":{"a":0,"k":0,"ix":4},"sa":{"a":0,"k":0,"ix":5},"nm":"Transform"}],"nm":"Group 2","np":3,"cix":2,"bm":0,"ix":2,"mn":"ADBE Vector Group","hd":false}],"ip":0,"op":75,"st":0,"ct":1,"bm":0},{"ddd":0,"ind":2,"ty":4,"nm":"team-outline-top_s1g1_s2g2_s3g1_s4g1_background Outlines","sr":1,"ks":{"o":{"a":0,"k":100,"ix":11},"r":{"a":0,"k":0,"ix":10},"p":{"a":0,"k":[24,24.74,0],"ix":2,"l":2},"a":{"a":0,"k":[24.25,14.759,0],"ix":1,"l":2},"s":{"a":0,"k":[100,100,100],"ix":6,"l":2}},"ao":0,"shapes":[{"ty":"gr","it":[{"ind":0,"ty":"sh","ix":1,"ks":{"a":1,"k":[{"i":{"x":0.667,"y":1},"o":{"x":0.333,"y":0},"t":18,"s":[{"i":[[0,2.278],[-2.277,0],[0,-2.278],[2.278,0]],"o":[[0,-2.278],[2.278,0],[0,2.278],[-2.277,0]],"v":[[-4.124,0],[-0.001,-4.124],[4.124,0],[-0.001,4.124]],"c":true}]},{"i":{"x":0.667,"y":1},"o":{"x":0.333,"y":0},"t":30.115,"s":[{"i":[[0,2.278],[-2.277,0],[0,-2.278],[2.278,0]],"o":[[0,-2.278],[2.278,0],[0,2.278],[-2.277,0]],"v":[[-4.094,-3.5],[0.03,-7.624],[4.155,-3.5],[0.03,0.624]],"c":true}]},{"t":42.162109375,"s":[{"i":[[0,2.278],[-2.277,0],[0,-2.278],[2.278,0]],"o":[[0,-2.278],[2.278,0],[0,2.278],[-2.277,0]],"v":[[-4.124,0],[-0.001,-4.124],[4.124,0],[-0.001,4.124]],"c":true}]}],"ix":2},"nm":"Path 1","mn":"ADBE Vector Shape - Group","hd":false},{"ty":"st","c":{"a":0,"k":[0.8549019607843137,0.15294117647058825,0.30196078431372547],"ix":3},"o":{"a":0,"k":100,"ix":4},"w":{"a":0,"k":2,"ix":5},"lc":2,"lj":2,"bm":0,"nm":"Stroke 1","mn":"ADBE Vector Graphic - Stroke","hd":false},{"ty":"fl","c":{"a":0,"k":[1,1,1],"ix":4},"o":{"a":0,"k":0,"ix":5},"r":1,"bm":0,"nm":"Fill 1","mn":"ADBE Vector Graphic - Fill","hd":false},{"ty":"tr","p":{"a":0,"k":[12.406,9.124],"ix":2},"a":{"a":0,"k":[0,0],"ix":1},"s":{"a":0,"k":[100,100],"ix":3},"r":{"a":0,"k":0,"ix":6},"o":{"a":0,"k":100,"ix":7},"sk":{"a":0,"k":0,"ix":4},"sa":{"a":0,"k":0,"ix":5},"nm":"Transform"}],"nm":"Group 1","np":3,"cix":2,"bm":0,"ix":1,"mn":"ADBE Vector Group","hd":false},{"ty":"gr","it":[{"ind":0,"ty":"sh","ix":1,"ks":{"a":1,"k":[{"i":{"x":0.667,"y":1},"o":{"x":0.333,"y":0},"t":18.068,"s":[{"i":[[0,-3.296],[0,0],[1.292,0],[0,0],[0,1.259],[-3.382,0],[0,0]],"o":[[0,0],[0,1.259],[0,0],[-1.292,0],[0,-3.296],[0,0],[3.382,0]],"v":[[7.406,1.844],[7.406,1.844],[5.066,4.124],[-5.066,4.124],[-7.406,1.844],[-1.281,-4.124],[1.281,-4.124]],"c":true}]},{"i":{"x":0.667,"y":1},"o":{"x":0.333,"y":0},"t":30.115,"s":[{"i":[[0,-3.296],[0,0],[1.292,0],[0,0],[0,1.259],[-3.382,0],[0,0]],"o":[[0,0],[0,1.259],[0,0],[-1.292,0],[0,-3.296],[0,0],[3.382,0]],"v":[[7.436,-1.656],[7.436,-1.656],[5.097,0.624],[-5.035,0.624],[-7.375,-1.656],[-1.251,-7.624],[1.312,-7.624]],"c":true}]},{"t":42.162109375,"s":[{"i":[[0,-3.296],[0,0],[1.292,0],[0,0],[0,1.259],[-3.382,0],[0,0]],"o":[[0,0],[0,1.259],[0,0],[-1.292,0],[0,-3.296],[0,0],[3.382,0]],"v":[[7.406,1.844],[7.406,1.844],[5.066,4.124],[-5.066,4.124],[-7.406,1.844],[-1.281,-4.124],[1.281,-4.124]],"c":true}]}],"ix":2},"nm":"Path 1","mn":"ADBE Vector Shape - Group","hd":false},{"ty":"st","c":{"a":0,"k":[0.8549019607843137,0.15294117647058825,0.30196078431372547],"ix":3},"o":{"a":0,"k":100,"ix":4},"w":{"a":0,"k":2,"ix":5},"lc":2,"lj":2,"bm":0,"nm":"Stroke 1","mn":"ADBE Vector Graphic - Stroke","hd":false},{"ty":"fl","c":{"a":0,"k":[1,1,1],"ix":4},"o":{"a":0,"k":0,"ix":5},"r":1,"bm":0,"nm":"Fill 1","mn":"ADBE Vector Graphic - Fill","hd":false},{"ty":"tr","p":{"a":0,"k":[12.405,20.394],"ix":2},"a":{"a":0,"k":[0,0],"ix":1},"s":{"a":0,"k":[100,100],"ix":3},"r":{"a":0,"k":0,"ix":6},"o":{"a":0,"k":100,"ix":7},"sk":{"a":0,"k":0,"ix":4},"sa":{"a":0,"k":0,"ix":5},"nm":"Transform"}],"nm":"Group 2","np":3,"cix":2,"bm":0,"ix":2,"mn":"ADBE Vector Group","hd":false},{"ty":"gr","it":[{"ind":0,"ty":"sh","ix":1,"ks":{"a":1,"k":[{"i":{"x":0.667,"y":1},"o":{"x":0.333,"y":0},"t":30,"s":[{"i":[[0,2.278],[-2.277,0],[0,-2.278],[2.278,0]],"o":[[0,-2.278],[2.278,0],[0,2.278],[-2.277,0]],"v":[[-4.124,0],[-0.001,-4.124],[4.124,0],[-0.001,4.124]],"c":true}]},{"i":{"x":0.667,"y":1},"o":{"x":0.333,"y":0},"t":42.162,"s":[{"i":[[0,2.278],[-2.277,0],[0,-2.278],[2.278,0]],"o":[[0,-2.278],[2.278,0],[0,2.278],[-2.277,0]],"v":[[-4.125,-2.75],[-0.001,-6.874],[4.124,-2.75],[-0.001,1.374]],"c":true}]},{"t":60,"s":[{"i":[[0,2.278],[-2.277,0],[0,-2.278],[2.278,0]],"o":[[0,-2.278],[2.278,0],[0,2.278],[-2.277,0]],"v":[[-4.124,0],[-0.001,-4.124],[4.124,0],[-0.001,4.124]],"c":true}]}],"ix":2},"nm":"Path 1","mn":"ADBE Vector Shape - Group","hd":false},{"ty":"st","c":{"a":0,"k":[0.8549019607843137,0.15294117647058825,0.30196078431372547],"ix":3},"o":{"a":0,"k":100,"ix":4},"w":{"a":0,"k":2,"ix":5},"lc":2,"lj":2,"bm":0,"nm":"Stroke 1","mn":"ADBE Vector Graphic - Stroke","hd":false},{"ty":"fl","c":{"a":0,"k":[1,1,1],"ix":4},"o":{"a":0,"k":0,"ix":5},"r":1,"bm":0,"nm":"Fill 1","mn":"ADBE Vector Graphic - Fill","hd":false},{"ty":"tr","p":{"a":0,"k":[36.095,9.124],"ix":2},"a":{"a":0,"k":[0,0],"ix":1},"s":{"a":0,"k":[100,100],"ix":3},"r":{"a":0,"k":0,"ix":6},"o":{"a":0,"k":100,"ix":7},"sk":{"a":0,"k":0,"ix":4},"sa":{"a":0,"k":0,"ix":5},"nm":"Transform"}],"nm":"Group 3","np":3,"cix":2,"bm":0,"ix":3,"mn":"ADBE Vector Group","hd":false},{"ty":"gr","it":[{"ind":0,"ty":"sh","ix":1,"ks":{"a":1,"k":[{"i":{"x":0.667,"y":1},"o":{"x":0.333,"y":0},"t":30,"s":[{"i":[[0,-3.296],[0,0],[1.292,0],[0,0],[0,1.259],[-3.382,0],[0,0]],"o":[[0,0],[0,1.259],[0,0],[-1.292,0],[0,-3.296],[0,0],[3.382,0]],"v":[[7.406,1.844],[7.406,1.844],[5.066,4.124],[-5.066,4.124],[-7.406,1.844],[-1.281,-4.124],[1.282,-4.124]],"c":true}]},{"i":{"x":0.667,"y":1},"o":{"x":0.333,"y":0},"t":42.162,"s":[{"i":[[0,-3.296],[0,0],[1.292,0],[0,0],[0,1.259],[-3.382,0],[0,0]],"o":[[0,0],[0,1.259],[0,0],[-1.292,0],[0,-3.296],[0,0],[3.382,0]],"v":[[7.405,-0.906],[7.405,-0.906],[5.066,1.374],[-5.066,1.374],[-7.406,-0.906],[-1.282,-6.874],[1.281,-6.874]],"c":true}]},{"t":60,"s":[{"i":[[0,-3.296],[0,0],[1.292,0],[0,0],[0,1.259],[-3.382,0],[0,0]],"o":[[0,0],[0,1.259],[0,0],[-1.292,0],[0,-3.296],[0,0],[3.382,0]],"v":[[7.406,1.844],[7.406,1.844],[5.066,4.124],[-5.066,4.124],[-7.406,1.844],[-1.281,-4.124],[1.282,-4.124]],"c":true}]}],"ix":2},"nm":"Path 1","mn":"ADBE Vector Shape - Group","hd":false},{"ty":"st","c":{"a":0,"k":[0.8549019607843137,0.15294117647058825,0.30196078431372547],"ix":3},"o":{"a":0,"k":100,"ix":4},"w":{"a":0,"k":2,"ix":5},"lc":2,"lj":2,"bm":0,"nm":"Stroke 1","mn":"ADBE Vector Graphic - Stroke","hd":false},{"ty":"fl","c":{"a":0,"k":[1,1,1],"ix":4},"o":{"a":0,"k":0,"ix":5},"r":1,"bm":0,"nm":"Fill 1","mn":"ADBE Vector Graphic - Fill","hd":false},{"ty":"tr","p":{"a":0,"k":[36.095,20.394],"ix":2},"a":{"a":0,"k":[0,0],"ix":1},"s":{"a":0,"k":[100,100],"ix":3},"r":{"a":0,"k":0,"ix":6},"o":{"a":0,"k":100,"ix":7},"sk":{"a":0,"k":0,"ix":4},"sa":{"a":0,"k":0,"ix":5},"nm":"Transform"}],"nm":"Group 4","np":3,"cix":2,"bm":0,"ix":4,"mn":"ADBE Vector Group","hd":false}],"ip":0,"op":75,"st":0,"ct":1,"bm":0}],"markers":[],"props":{}}